diffstrings/__init__.py
diffstrings/color_diff.py
diffstrings-0.1.3.dist-info/METADATA
diffstrings-0.1.3.dist-info/WHEEL
diffstrings-0.1.3.dist-info/licenses/LICENSE
diffstrings-0.1.3.dist-info/RECORD
