Metadata-Version: 2.1
Name: diffstrings
Version: 0.1.3
Summary: Show difference of two strings in color
Project-URL: Homepage, https://github.com/uguudei/diffstrings
Project-URL: Bug Tracker, https://github.com/uguudei/diffstrings/issues
Project-URL: Source Code, https://github.com/uguudei/diffstrings
Author: Uguudei
License-File: LICENSE
Classifier: License :: OSI Approved :: MIT License
Classifier: Operating System :: OS Independent
Classifier: Programming Language :: Python
Classifier: Programming Language :: Python :: 3
Classifier: Programming Language :: Python :: 3 :: Only
Classifier: Programming Language :: Python :: 3.7
Classifier: Programming Language :: Python :: 3.8
Classifier: Programming Language :: Python :: 3.9
Classifier: Programming Language :: Python :: 3.10
Classifier: Programming Language :: Python :: 3.11
Requires-Python: >=3.7
